multiversity/__init__.py
multiversity/multi_labeler.py
multiversity/multicare_creator.py
multiversity/multicare_dataset.py
multiversity/multicare_v1.py
multiversity/multiplex_classification.py
multiversity/data/GT_MCR_TX_input_format.owx
multiversity/data/ML_MCT_TX_input_format.owx
multiversity/data/annotated_ngrams.csv
multiversity-2.0.8.dist-info/LICENSE.txt
multiversity-2.0.8.dist-info/METADATA
multiversity-2.0.8.dist-info/WHEEL
multiversity-2.0.8.dist-info/top_level.txt
multiversity-2.0.8.dist-info/RECORD
